ccvfi/__init__.py
ccvfi/arch/__init__.py
ccvfi/arch/arch_utils/softsplat.py
ccvfi/arch/arch_utils/softsplat_torch.py
ccvfi/arch/arch_utils/warplayer.py
ccvfi/arch/drba_arch.py
ccvfi/arch/ifnet_arch.py
ccvfi/auto/__init__.py
ccvfi/auto/config.py
ccvfi/auto/model.py
ccvfi/cache_models/__init__.py
ccvfi/config/__init__.py
ccvfi/config/drba_config.py
ccvfi/config/rife_config.py
ccvfi/model/__init__.py
ccvfi/model/drba_model.py
ccvfi/model/rife_model.py
ccvfi/model/vfi_base_model.py
ccvfi/type/__init__.py
ccvfi/type/arch.py
ccvfi/type/base_config.py
ccvfi/type/base_model.py
ccvfi/type/config.py
ccvfi/type/model.py
ccvfi/util/__init__.py
ccvfi/util/color.py
ccvfi/util/device.py
ccvfi/util/misc.py
ccvfi/util/registry.py
ccvfi/vs/__init__.py
ccvfi/vs/convert.py
ccvfi/vs/vfi.py
ccvfi-0.0.3.dist-info/LICENSE
ccvfi-0.0.3.dist-info/METADATA
ccvfi-0.0.3.dist-info/WHEEL
ccvfi-0.0.3.dist-info/RECORD
